bioconsertinc.cp311-win_amd64.pyd
bioconsertinc-2.0.2.dist-info/LICENSE
bioconsertinc-2.0.2.dist-info/METADATA
bioconsertinc-2.0.2.dist-info/WHEEL
bioconsertinc-2.0.2.dist-info/top_level.txt
bioconsertinc-2.0.2.dist-info/RECORD
