Metadata-Version: 2.1
Name: bioconsertinc
Version: 2.0.2
Summary: BioConsert, c implementation
Home-page: https://github.com/pierreandrieu/bioconsertinc
Author: Pierre Andrieu
Author-email: pierre.andrieu@lilo.org
License: MIT
Requires-Python: >=3.8
License-File: LICENSE
Requires-Dist: numpy (>=1.24.0)
